dynmap_lens/__init__.py
dynmap_lens/dynmap.py
dynmap_lens/projection.py
dynmap_lens/simple_downloader.py
dynmap_lens/time_machine.py
dynmap_lens-1.0.0.data/scripts/dynmap-lens.py
dynmap_lens-1.0.0.dist-info/LICENSE
dynmap_lens-1.0.0.dist-info/METADATA
dynmap_lens-1.0.0.dist-info/WHEEL
dynmap_lens-1.0.0.dist-info/top_level.txt
dynmap_lens-1.0.0.dist-info/RECORD
